modal_forms/__init__.py
modal_forms/apps.py
modal_forms/modal_form.py
modal_forms/static/modal_forms/js/script.js
modal_forms/templates/modal_forms/bootstrap3/form_horizontal.html
modal_forms/templates/modal_forms/bootstrap4/form_horizontal.html
django_modal_forms-2.0.dist-info/LICENSE
django_modal_forms-2.0.dist-info/METADATA
django_modal_forms-2.0.dist-info/WHEEL
django_modal_forms-2.0.dist-info/top_level.txt
django_modal_forms-2.0.dist-info/RECORD
